kafkagraph/__init__.py
kafkagraph/client.py
kafkagraph/core/batcher.py
kafkagraph/core/consumer.py
kafkagraph/core/dispatcher.py
kafkagraph/core/engine.py
kafkagraph/core/partition_monitor.py
kafkagraph/license/api_key_manager.py
kafkagraph/license/api_keys.py
kafkagraph/license/features.py
kafkagraph/license/fingerprint.py
kafkagraph/license/manager.py
kafkagraph/license/rate_limiter.py
kafkagraph/license/signed.py
kafkagraph/mappers/autograph.py
kafkagraph/mappers/sequence.py
kafkagraph/mappers/simple.py
kafkagraph/neo4j/writer.py
kafkagraph/utils/time.py
kafkagraph-0.1.2.dist-info/licenses/LICENSE
kafkagraph-0.1.2.dist-info/METADATA
kafkagraph-0.1.2.dist-info/WHEEL
kafkagraph-0.1.2.dist-info/top_level.txt
kafkagraph-0.1.2.dist-info/RECORD
