Metadata-Version: 2.4
Name: kafkagraph
Version: 0.1.2
Summary: Licensed Kafka to Neo4j Graph Ingestion Engine for turn-key graph building
Author: Siddhappa Birajdar
License-Expression: LicenseRef-Proprietary
Project-URL: Homepage, https://www.linkedin.com/in/siddhappabirajdar
Project-URL: Source, https://github.com/siddhappa/kafkagraph
Project-URL: Documentation, https://pypi.org/project/kafkagraph
Keywords: kafka,neo4j,graph,ingestion,etl,data-engineering,python-sdk,enterprise-license
Classifier: Programming Language :: Python :: 3
Classifier: Operating System :: OS Independent
Requires-Python: >=3.9
License-File: LICENSE
Requires-Dist: kafka-python
Requires-Dist: neo4j
Requires-Dist: pyyaml
Requires-Dist: pynacl
Dynamic: license-file
